pysqldq/__init__.py
pysqldq/dqchecks.py
pysqldq-0.0.2.dist-info/LICENSE
pysqldq-0.0.2.dist-info/METADATA
pysqldq-0.0.2.dist-info/WHEEL
pysqldq-0.0.2.dist-info/top_level.txt
pysqldq-0.0.2.dist-info/RECORD
