Metadata-Version: 2.1
Name: pysqldq
Version: 0.0.2
Summary: A library to create dynamic SQL data quality checks
Home-page: https://github.com/pysqldq-project/pysqldq/
Author: Akshay Katre
Author-email: akshaykatre@gmail.com
License: UNKNOWN
Platform: UNKNOWN
Classifier: Programming Language :: Python :: 3.7
Classifier: License :: OSI Approved :: GNU Affero General Public License v3 or later (AGPLv3+)
